xia_user/__init__.py
xia_user/messages.cpython-39-darwin.so
xia_user/role_matrix.cpython-39-darwin.so
xia_user/user.cpython-39-darwin.so
xia_user-0.1.33.dist-info/LICENSE.txt
xia_user-0.1.33.dist-info/METADATA
xia_user-0.1.33.dist-info/WHEEL
xia_user-0.1.33.dist-info/top_level.txt
xia_user-0.1.33.dist-info/RECORD
