Metadata-Version: 2.1
Name: xia-user
Version: 0.1.33
Summary: xia-user
Home-page: https://develop.x-i-a.com/docs/xia-user/0.1.33/index.html
Author: X-I-A
Author-email: admin@x-i-a.com
License: UNKNOWN
Platform: UNKNOWN
Requires-Python: >=3.9
License-File: LICENSE.txt
Requires-Dist: passlib
Requires-Dist: xia-fields-network
Requires-Dist: xia-engine
Requires-Dist: xia-fields
